umrx_app_v3/__init__.py
umrx_app_v3/mcu_board/__init__.py
umrx_app_v3/mcu_board/app_board_v3_rev0.py
umrx_app_v3/mcu_board/app_board_v3_rev1.py
umrx_app_v3/mcu_board/bst_app_board.py
umrx_app_v3/mcu_board/bst_protocol.py
umrx_app_v3/mcu_board/bst_protocol_constants.py
umrx_app_v3/mcu_board/comm/__init__.py
umrx_app_v3/mcu_board/comm/comm.py
umrx_app_v3/mcu_board/comm/serial_comm.py
umrx_app_v3/mcu_board/comm/usb_comm.py
umrx_app_v3/mcu_board/commands/__init__.py
umrx_app_v3/mcu_board/commands/app_switch.py
umrx_app_v3/mcu_board/commands/board_info.py
umrx_app_v3/mcu_board/commands/command.py
umrx_app_v3/mcu_board/commands/i2c.py
umrx_app_v3/mcu_board/commands/pin_config.py
umrx_app_v3/mcu_board/commands/set_vdd_vddio.py
umrx_app_v3/mcu_board/commands/spi.py
umrx_app_v3/mcu_board/commands/streaming_interrupt.py
umrx_app_v3/mcu_board/commands/streaming_polling.py
umrx_app_v3/mcu_board/commands/timer.py
umrx_app_v3/sensors/__init__.py
umrx_app_v3/sensors/bma400.py
umrx_app_v3/sensors/bma456.py
umrx_app_v3/sensors/bma530.py
umrx_app_v3/sensors/bma580.py
umrx_app_v3/sensors/bme280.py
umrx_app_v3/sensors/bmi088.py
umrx_app_v3/sensors/bmi323.py
umrx_app_v3/sensors/bmm350.py
umrx_app_v3/sensors/bmp390.py
umrx_app_v3/sensors/bmp585.py
umrx_app_v3/shuttle_board/__init__.py
umrx_app_v3/shuttle_board/bma400/__init__.py
umrx_app_v3/shuttle_board/bma400/bma400_shuttle.py
umrx_app_v3/shuttle_board/bma456/__init__.py
umrx_app_v3/shuttle_board/bma456/bma456_shuttle.py
umrx_app_v3/shuttle_board/bma456/config_files/__init__.py
umrx_app_v3/shuttle_board/bma456/config_files/bma456_an.py
umrx_app_v3/shuttle_board/bma456/config_files/bma456_h.py
umrx_app_v3/shuttle_board/bma456/config_files/bma456_mm.py
umrx_app_v3/shuttle_board/bma456/config_files/bma456_tablet.py
umrx_app_v3/shuttle_board/bma456/config_files/bma456_w.py
umrx_app_v3/shuttle_board/bma530/__init__.py
umrx_app_v3/shuttle_board/bma530/bma530_shuttle.py
umrx_app_v3/shuttle_board/bma580/__init__.py
umrx_app_v3-1.8.0.dist-info/METADATA
umrx_app_v3-1.8.0.dist-info/WHEEL
umrx_app_v3-1.8.0.dist-info/licenses/LICENSE
umrx_app_v3-1.8.0.dist-info/RECORD
