Metadata-Version: 2.4
Name: umrx-app-v3
Version: 1.8.0
Summary: Communication with COINES firmware for humans
License-File: LICENSE
Author: Konstantin Selyunin
Author-email: selyunin.k.v@gmail.com
Requires-Python: >=3.12,<4.0
Classifier: Programming Language :: Python :: 3
Classifier: Programming Language :: Python :: 3.12
Classifier: Programming Language :: Python :: 3.13
Classifier: Programming Language :: Python :: 3.14
Requires-Dist: pyserial (==3.5)
Requires-Dist: pyusb (>=1.3.1)
